{"index":{"apiVersion":"v1","generated":"2023-09-13T13:59:38.619574678Z","entries":{"agent":[{"name":"agent","version":"0.0.1-nightly+e56ff1b","description":"Helm cart for deploying TIS agent.","apiVersion":"v2","appVersion":"0.0.1-nightly+e56ff1b","annotations":{"tetrate.io/system":"true"},"urls":["system/agent-0.0.1-nightly+e56ff1b.tgz"],"created":"2023-09-13T13:59:38.615754498Z","digest":"8b6f4c64bab3c92f6795e746fb3c6ec313bcbf8e6fe719cd505f2c199ed871ef"},{"name":"agent","version":"0.0.1","description":"Helm cart for deploying TIS agent.","apiVersion":"v2","appVersion":"0.0.1-nightly+e56ff1b","annotations":{"tetrate.io/system":"true"},"urls":["system/agent-0.0.1.tgz"],"created":"2023-09-13T13:59:06.147926088Z","digest":"74c7f7d66980acf11278a81a1c0b6a52e80308d94ac635c912e3ce838bc3dd46"}],"base":[{"name":"base","sources":["http://github.com/istio/istio"],"version":"1.13.3","description":"Helm chart for deploying Istio cluster resources and CRDs","keywords":["istio"],"icon":"https://istio.io/latest/favicons/android-192x192.png","apiVersion":"v1","appVersion":"1.13.3-tetrate-v0","urls":["istio/1.13.3/base-1.13.3.tgz"],"created":"2022-05-04T21:03:38Z","digest":"423d9e4e984999c373330fa4cbab3112579b0c419b1b92320170cecc28889e0b"},{"name":"base","sources":["http://github.com/istio/istio"],"version":"1.13.5","description":"Helm chart for deploying Istio cluster resources and CRDs","keywords":["istio"],"icon":"https://istio.io/latest/favicons/android-192x192.png","apiVersion":"v1","appVersion":"1.13.5-tetrate-v0","urls":["istio/1.13.5/base-1.13.5.tgz"],"created":"2022-06-13T16:19:44Z","digest":"f48fee9dc3431bc7a898d62e0080f7190e6bc19b13f5e128cd90b18fd5269738"},{"name":"base","sources":["http://github.com/istio/istio"],"version":"1.14.1","description":"Helm chart for deploying Istio cluster resources and CRDs","keywords":["istio"],"icon":"https://istio.io/latest/favicons/android-192x192.png","apiVersion":"v1","appVersion":"1.14.1-tetrate-v0","urls":["istio/1.14.1/base-1.14.1.tgz"],"created":"2022-07-07T15:27:26Z","digest":"619122d982f801015cc7b4c7d908e7e31ccd401371c16762ab86878ecd549a7b"},{"name":"base","sources":["http://github.com/istio/istio"],"version":"1.14.3","description":"Helm chart for deploying Istio cluster resources and CRDs","keywords":["istio"],"icon":"https://istio.io/latest/favicons/android-192x192.png","apiVersion":"v1","appVersion":"1.14.3-tetrate-v0","urls":["istio/1.14.3/base-1.14.3.tgz"],"created":"2022-08-05T15:02:57Z","digest":"c1c30c8d0b0f07745b1dbdf83b338e57f3873f2cd19cf81f61b0506a0ffa0977"},{"name":"base","sources":["http://github.com/istio/istio"],"version":"1.14.5","description":"Helm chart for deploying Istio cluster resources and CRDs","keywords":["istio"],"icon":"https://istio.io/latest/favicons/android-192x192.png","apiVersion":"v1","appVersion":"1.14.5-tetrate-v0","urls":["istio/1.14.5/base-1.14.5.tgz"],"created":"2022-10-27T21:03:09Z","digest":"a22b9ae10b70e5e42fa68ebf317fabdab552444bb7e5b755cd387ac5e479d8f4"},{"name":"base","sources":["http://github.com/istio/istio"],"version":"1.14.6","description":"Helm chart for deploying Istio cluster resources and CRDs","keywords":["istio"],"icon":"https://istio.io/latest/favicons/android-192x192.png","apiVersion":"v1","appVersion":"1.14.6-tetrate-v0","urls":["istio/1.14.6/base-1.14.6.tgz"],"created":"2022-12-14T19:21:21Z","digest":"5c6c98e5c7ab07b07fc1ffee4e270714e1f4132d43869359bbd1196a0c43204b"},{"name":"base","sources":["http://github.com/istio/istio"],"version":"1.15.4","description":"Helm chart for deploying Istio cluster resources and CRDs","keywords":["istio"],"icon":"https://istio.io/latest/favicons/android-192x192.png","apiVersion":"v1","appVersion":"1.15.4-tetrate-v0","urls":["istio/1.15.4/base-1.15.4.tgz"],"created":"2023-01-24T00:42:53Z","digest":"ff820f9605ebbe0d63d1218089afec693bc43381cf499b996ac71b60b8993e4f"},{"name":"base","sources":["http://github.com/istio/istio"],"version":"1.16.2","description":"Helm chart for deploying Istio cluster resources and CRDs","keywords":["istio"],"icon":"https://istio.io/latest/favicons/android-192x192.png","apiVersion":"v1","appVersion":"1.16.2-tetrate-v0","urls":["istio/1.16.2/base-1.16.2.tgz"],"created":"2023-02-05T16:43:09Z","digest":"0f35086259e711abf754cd0fd675551609069c3a78fd9a074db812059712b21c"},{"name":"base","sources":["http://github.com/istio/istio"],"version":"1.16.4","description":"Helm chart for deploying Istio cluster resources and CRDs","keywords":["istio"],"icon":"https://istio.io/latest/favicons/android-192x192.png","apiVersion":"v1","appVersion":"1.16.4-tetrate-v4","urls":["istio/1.16.4/base-1.16.4.tgz"],"created":"2023-07-19T06:52:29Z","digest":"debad0fbac278ffc71dd6f89f90328046646fbbf18b5c14512d6a7f92018e5e0"},{"name":"base","sources":["http://github.com/istio/istio"],"version":"1.16.5","description":"Helm chart for deploying Istio cluster resources and CRDs","keywords":["istio"],"icon":"https://istio.io/latest/favicons/android-192x192.png","apiVersion":"v1","appVersion":"1.16.5-tetrate-v0","urls":["istio/1.16.5/base-1.16.5.tgz"],"created":"2023-05-26T03:29:11Z","digest":"450407b304e073c548e4442a742e90d3c57ef829d16d6b147e551c7e9593e7b4"},{"name":"base","sources":["http://github.com/istio/istio"],"version":"1.16.7","description":"Helm chart for deploying Istio cluster resources and CRDs","keywords":["istio"],"icon":"https://istio.io/latest/favicons/android-192x192.png","apiVersion":"v1","appVersion":"1.16.7-tetrate-v0","urls":["istio/1.16.7/base-1.16.7.tgz"],"created":"2023-07-28T16:04:01Z","digest":"54abe18707655fb4ba142d116482add267c9b6a6a0cf278ed685282f65402e83"},{"name":"base","sources":["http://github.com/istio/istio"],"version":"1.17.1","description":"Helm chart for deploying Istio cluster resources and CRDs","keywords":["istio"],"icon":"https://istio.io/latest/favicons/android-192x192.png","apiVersion":"v1","appVersion":"1.17.1-tetrate-v0","urls":["istio/1.17.1/base-1.17.1.tgz"],"created":"2023-02-27T03:57:23Z","digest":"40320a0e36f110341a0fe62456b8f0ecd52d58e9a3bae5cb7d583d059e8a0fd0"},{"name":"base","sources":["http://github.com/istio/istio"],"version":"1.17.3","description":"Helm chart for deploying Istio cluster resources and CRDs","keywords":["istio"],"icon":"https://istio.io/latest/favicons/android-192x192.png","apiVersion":"v1","appVersion":"1.17.3-tetrate-v0","urls":["istio/1.17.3/base-1.17.3.tgz"],"created":"2023-06-09T14:50:25Z","digest":"efabd09642951a305d4620ace59ca50d05ce43e781310d87e67671070708678d"},{"name":"base","sources":["http://github.com/istio/istio"],"version":"1.17.5","description":"Helm chart for deploying Istio cluster resources and CRDs","keywords":["istio"],"icon":"https://istio.io/latest/favicons/android-192x192.png","apiVersion":"v1","appVersion":"1.17.5-tetrate-v0","urls":["istio/1.17.5/base-1.17.5.tgz"],"created":"2023-07-28T15:12:44Z","digest":"611641ea150d2c58b2598f4208ae498e97a6d9e92c56fc57262e2c9491e61fea"},{"name":"base","sources":["https://github.com/istio/istio"],"version":"1.18.0","description":"Helm chart for deploying Istio cluster resources and CRDs","keywords":["istio"],"icon":"https://istio.io/latest/favicons/android-192x192.png","apiVersion":"v1","appVersion":"1.18.0-tetrate-v0","urls":["istio/1.18.0/base-1.18.0.tgz"],"created":"2023-06-09T16:41:21Z","digest":"2b5392a5311c3caac09f61565cd65a4a4a0af325dffd5604d70731f4916e223a"},{"name":"base","sources":["https://github.com/istio/istio"],"version":"1.18.2","description":"Helm chart for deploying Istio cluster resources and CRDs","keywords":["istio"],"icon":"https://istio.io/latest/favicons/android-192x192.png","apiVersion":"v1","appVersion":"1.18.2-tetrate-v0","urls":["istio/1.18.2/base-1.18.2.tgz"],"created":"2023-07-28T15:46:16Z","digest":"c70249a967d790a78d66a3ba77ce22bc0477604e7da37d1452d7d3f7015b8c5a"}],"cni":[{"name":"cni","sources":["http://github.com/istio/cni"],"version":"1.13.3","description":"Helm chart for istio-cni components","keywords":["istio-cni","istio"],"icon":"https://istio.io/latest/favicons/android-192x192.png","apiVersion":"v1","appVersion":"1.13.3-tetrate-v0","urls":["istio/1.13.3/cni-1.13.3.tgz"],"created":"2022-05-04T21:03:38Z","digest":"17bc3aca575a116d40581777fb6455eb2aa99cf4567a841d47866bc83a65f4bc"},{"name":"cni","sources":["http://github.com/istio/cni"],"version":"1.13.5","description":"Helm chart for istio-cni components","keywords":["istio-cni","istio"],"icon":"https://istio.io/latest/favicons/android-192x192.png","apiVersion":"v1","appVersion":"1.13.5-tetrate-v0","urls":["istio/1.13.5/cni-1.13.5.tgz"],"created":"2022-06-13T16:19:44Z","digest":"00782068e15ee0aa068987a5f6aeb50283e3e27f8f92328933881bce6f23f505"},{"name":"cni","sources":["http://github.com/istio/cni"],"version":"1.14.1","description":"Helm chart for istio-cni components","keywords":["istio-cni","istio"],"icon":"https://istio.io/latest/favicons/android-192x192.png","apiVersion":"v1","appVersion":"1.14.1-tetrate-v0","urls":["istio/1.14.1/cni-1.14.1.tgz"],"created":"2022-07-07T15:27:26Z","digest":"a715c74dd21007f748adb68720af9ea98a4d3a3f103956b06451841f39e7e08a"},{"name":"cni","sources":["http://github.com/istio/cni"],"version":"1.14.3","description":"Helm chart for istio-cni components","keywords":["istio-cni","istio"],"icon":"https://istio.io/latest/favicons/android-192x192.png","apiVersion":"v1","appVersion":"1.14.3-tetrate-v0","urls":["istio/1.14.3/cni-1.14.3.tgz"],"created":"2022-08-05T15:02:57Z","digest":"dc46045c09cf95d4965fcc5b1806b2dc1339a2cb3db560b676927026d0a815d1"},{"name":"cni","sources":["http://github.com/istio/cni"],"version":"1.14.5","description":"Helm chart for istio-cni components","keywords":["istio-cni","istio"],"icon":"https://istio.io/latest/favicons/android-192x192.png","apiVersion":"v1","appVersion":"1.14.5-tetrate-v0","urls":["istio/1.14.5/cni-1.14.5.tgz"],"created":"2022-10-27T21:03:09Z","digest":"df791d4acb2ca16e7638cf47351c461912645f0c7b0b3b05bdc21f3eb581abf3"},{"name":"cni","sources":["http://github.com/istio/cni"],"version":"1.14.6","description":"Helm chart for istio-cni components","keywords":["istio-cni","istio"],"icon":"https://istio.io/latest/favicons/android-192x192.png","apiVersion":"v1","appVersion":"1.14.6-tetrate-v0","urls":["istio/1.14.6/cni-1.14.6.tgz"],"created":"2022-12-14T19:21:21Z","digest":"e2d0b9b76f77ae6552450ad39f9021d1953d6938887045a46d2e442ace9cc3e8"},{"name":"cni","sources":["http://github.com/istio/cni"],"version":"1.15.4","description":"Helm chart for istio-cni components","keywords":["istio-cni","istio"],"icon":"https://istio.io/latest/favicons/android-192x192.png","apiVersion":"v1","appVersion":"1.15.4-tetrate-v0","urls":["istio/1.15.4/cni-1.15.4.tgz"],"created":"2023-01-24T00:42:53Z","digest":"3fd9b4489c4c12f35c59ea821f63974651d1978553c6f66cd6c19efe7a1ae4f9"},{"name":"cni","sources":["https://github.com/istio/istio/tree/master/cni"],"version":"1.16.2","description":"Helm chart for istio-cni components","keywords":["istio-cni","istio"],"icon":"https://istio.io/latest/favicons/android-192x192.png","apiVersion":"v1","appVersion":"1.16.2-tetrate-v0","urls":["istio/1.16.2/cni-1.16.2.tgz"],"created":"2023-02-05T16:43:09Z","digest":"74c466cde2e9faeff50b211434b0ff477300725830093b1197338bfe174892d5"},{"name":"cni","sources":["https://github.com/istio/istio/tree/master/cni"],"version":"1.16.4","description":"Helm chart for istio-cni components","keywords":["istio-cni","istio"],"icon":"https://istio.io/latest/favicons/android-192x192.png","apiVersion":"v1","appVersion":"1.16.4-tetrate-v4","urls":["istio/1.16.4/cni-1.16.4.tgz"],"created":"2023-07-19T06:52:29Z","digest":"e9eeb95e26bf70b47673e968dccf97a42ad6dab356304ea2e7504b9d22c748ef"},{"name":"cni","sources":["https://github.com/istio/istio/tree/master/cni"],"version":"1.16.5","description":"Helm chart for istio-cni components","keywords":["istio-cni","istio"],"icon":"https://istio.io/latest/favicons/android-192x192.png","apiVersion":"v1","appVersion":"1.16.5-tetrate-v0","urls":["istio/1.16.5/cni-1.16.5.tgz"],"created":"2023-05-26T03:29:11Z","digest":"33420389d28c0beefadba8a43742c0ad7c21835af7f65780b163cac1996cf02f"},{"name":"cni","sources":["https://github.com/istio/istio/tree/master/cni"],"version":"1.16.7","description":"Helm chart for istio-cni components","keywords":["istio-cni","istio"],"icon":"https://istio.io/latest/favicons/android-192x192.png","apiVersion":"v1","appVersion":"1.16.7-tetrate-v0","urls":["istio/1.16.7/cni-1.16.7.tgz"],"created":"2023-07-28T16:04:01Z","digest":"1180e4226b1ec156035837bc6769df57ab8a85a06d370a3641cba5839279fca6"},{"name":"cni","sources":["https://github.com/istio/istio/tree/master/cni"],"version":"1.17.1","description":"Helm chart for istio-cni components","keywords":["istio-cni","istio"],"icon":"https://istio.io/latest/favicons/android-192x192.png","apiVersion":"v1","appVersion":"1.17.1-tetrate-v0","urls":["istio/1.17.1/cni-1.17.1.tgz"],"created":"2023-02-27T03:57:23Z","digest":"1ccee5f5a1f0886ab67f5d5e8068202695d7555bf41ba0d91839f028c445eb6b"},{"name":"cni","sources":["https://github.com/istio/istio/tree/master/cni"],"version":"1.17.3","description":"Helm chart for istio-cni components","keywords":["istio-cni","istio"],"icon":"https://istio.io/latest/favicons/android-192x192.png","apiVersion":"v1","appVersion":"1.17.3-tetrate-v0","urls":["istio/1.17.3/cni-1.17.3.tgz"],"created":"2023-06-09T14:50:25Z","digest":"9805594724e2f0b92c910135d154affb894c51ce4e5ad1c0e6406212a9a5c4a3"},{"name":"cni","sources":["https://github.com/istio/istio/tree/master/cni"],"version":"1.17.5","description":"Helm chart for istio-cni components","keywords":["istio-cni","istio"],"icon":"https://istio.io/latest/favicons/android-192x192.png","apiVersion":"v1","appVersion":"1.17.5-tetrate-v0","urls":["istio/1.17.5/cni-1.17.5.tgz"],"created":"2023-07-28T15:12:44Z","digest":"1ecb662160bf2351242ddcfb4fea986a37f8ca37ff40b3a25aef16b4c75810cf"},{"name":"cni","sources":["https://github.com/istio/istio/tree/master/cni"],"version":"1.18.0","description":"Helm chart for istio-cni components","keywords":["istio-cni","istio"],"icon":"https://istio.io/latest/favicons/android-192x192.png","apiVersion":"v1","appVersion":"1.18.0-tetrate-v0","urls":["istio/1.18.0/cni-1.18.0.tgz"],"created":"2023-06-09T16:41:21Z","digest":"76ace07bbcc0d035a1e23818916f107bba87214e5ee3a615b7f8bebd432b70e0"},{"name":"cni","sources":["https://github.com/istio/istio/tree/master/cni"],"version":"1.18.2","description":"Helm chart for istio-cni components","keywords":["istio-cni","istio"],"icon":"https://istio.io/latest/favicons/android-192x192.png","apiVersion":"v1","appVersion":"1.18.2-tetrate-v0","urls":["istio/1.18.2/cni-1.18.2.tgz"],"created":"2023-07-28T15:46:16Z","digest":"0f3405f5edc50c81ab941fd29c4ad95f7d8a608571ba256a603e2a7e52155f59"}],"gateway":[{"name":"gateway","sources":["http://github.com/istio/istio"],"version":"1.13.3","description":"Helm chart for deploying Istio gateways","keywords":["istio","gateways"],"icon":"https://istio.io/latest/favicons/android-192x192.png","apiVersion":"v2","appVersion":"1.13.3-tetrate-v0","type":"application","urls":["istio/1.13.3/gateway-1.13.3.tgz"],"created":"2022-05-04T21:03:38Z","digest":"736441d8757d0bbaf527a9c9e98dbeb26b958d8be4419c650756a64e8eaa8a69"},{"name":"gateway","sources":["http://github.com/istio/istio"],"version":"1.13.5","description":"Helm chart for deploying Istio gateways","keywords":["istio","gateways"],"icon":"https://istio.io/latest/favicons/android-192x192.png","apiVersion":"v2","appVersion":"1.13.5-tetrate-v0","type":"application","urls":["istio/1.13.5/gateway-1.13.5.tgz"],"created":"2022-06-13T16:19:44Z","digest":"e9e8765f3c0370878cfb777c6b1b1e47d0ae989bb30e5dc6ab6fa6bdbd058b05"},{"name":"gateway","sources":["http://github.com/istio/istio"],"version":"1.14.1","description":"Helm chart for deploying Istio gateways","keywords":["istio","gateways"],"icon":"https://istio.io/latest/favicons/android-192x192.png","apiVersion":"v2","appVersion":"1.14.1-tetrate-v0","type":"application","urls":["istio/1.14.1/gateway-1.14.1.tgz"],"created":"2022-07-07T15:27:26Z","digest":"a322d37b9cf0cf5b94736603669eae231f6137d5ec29785f227c32610e0fad05"},{"name":"gateway","sources":["http://github.com/istio/istio"],"version":"1.14.3","description":"Helm chart for deploying Istio gateways","keywords":["istio","gateways"],"icon":"https://istio.io/latest/favicons/android-192x192.png","apiVersion":"v2","appVersion":"1.14.3-tetrate-v0","type":"application","urls":["istio/1.14.3/gateway-1.14.3.tgz"],"created":"2022-08-05T15:02:57Z","digest":"4031fb43e952452b6a346067cf6598d96fc5c83a6d9e8eca60087246b4445072"},{"name":"gateway","sources":["http://github.com/istio/istio"],"version":"1.14.5","description":"Helm chart for deploying Istio gateways","keywords":["istio","gateways"],"icon":"https://istio.io/latest/favicons/android-192x192.png","apiVersion":"v2","appVersion":"1.14.5-tetrate-v0","type":"application","urls":["istio/1.14.5/gateway-1.14.5.tgz"],"created":"2022-10-27T21:03:09Z","digest":"bea574fd2253eb1185be4364946a501b47e59a3d0d68d9afe3042fc1a4111474"},{"name":"gateway","sources":["http://github.com/istio/istio"],"version":"1.14.6","description":"Helm chart for deploying Istio gateways","keywords":["istio","gateways"],"icon":"https://istio.io/latest/favicons/android-192x192.png","apiVersion":"v2","appVersion":"1.14.6-tetrate-v0","type":"application","urls":["istio/1.14.6/gateway-1.14.6.tgz"],"created":"2022-12-14T19:21:21Z","digest":"51516030a360a7020de660327cc5accd042707a39d20f94d419be168e43426a5"},{"name":"gateway","sources":["http://github.com/istio/istio"],"version":"1.15.4","description":"Helm chart for deploying Istio gateways","keywords":["istio","gateways"],"icon":"https://istio.io/latest/favicons/android-192x192.png","apiVersion":"v2","appVersion":"1.15.4-tetrate-v0","type":"application","urls":["istio/1.15.4/gateway-1.15.4.tgz"],"created":"2023-01-24T00:42:53Z","digest":"8d07e235e0b0eb481b303b7cc5886c9512c3fb44342d164dc573ecea950e44c1"},{"name":"gateway","sources":["http://github.com/istio/istio"],"version":"1.16.2","description":"Helm chart for deploying Istio gateways","keywords":["istio","gateways"],"icon":"https://istio.io/latest/favicons/android-192x192.png","apiVersion":"v2","appVersion":"1.16.2-tetrate-v0","type":"application","urls":["istio/1.16.2/gateway-1.16.2.tgz"],"created":"2023-02-05T16:43:09Z","digest":"f0792dd77125ee0082dbc197cb1be1a93a18c95fea755ca168ec2d244deeddbe"},{"name":"gateway","sources":["http://github.com/istio/istio"],"version":"1.16.4","description":"Helm chart for deploying Istio gateways","keywords":["istio","gateways"],"icon":"https://istio.io/latest/favicons/android-192x192.png","apiVersion":"v2","appVersion":"1.16.4-tetrate-v4","type":"application","urls":["istio/1.16.4/gateway-1.16.4.tgz"],"created":"2023-07-19T06:52:29Z","digest":"ca753233aee4b1ee56fc6ca06d39ac369bcab5939c63e46eaf4dd358d8c72fdc"},{"name":"gateway","sources":["http://github.com/istio/istio"],"version":"1.16.5","description":"Helm chart for deploying Istio gateways","keywords":["istio","gateways"],"icon":"https://istio.io/latest/favicons/android-192x192.png","apiVersion":"v2","appVersion":"1.16.5-tetrate-v0","type":"application","urls":["istio/1.16.5/gateway-1.16.5.tgz"],"created":"2023-05-26T03:29:11Z","digest":"2958bb92eda204194bba19026731d7be55db4fa5b99025cb11680256ff7c295d"},{"name":"gateway","sources":["http://github.com/istio/istio"],"version":"1.16.7","description":"Helm chart for deploying Istio gateways","keywords":["istio","gateways"],"icon":"https://istio.io/latest/favicons/android-192x192.png","apiVersion":"v2","appVersion":"1.16.7-tetrate-v0","type":"application","urls":["istio/1.16.7/gateway-1.16.7.tgz"],"created":"2023-07-28T16:04:01Z","digest":"28fb3c3e93e34618081c7a28f714080bcd9dc526d8be703464fe31b89336f0ee"},{"name":"gateway","sources":["http://github.com/istio/istio"],"version":"1.17.1","description":"Helm chart for deploying Istio gateways","keywords":["istio","gateways"],"icon":"https://istio.io/latest/favicons/android-192x192.png","apiVersion":"v2","appVersion":"1.17.1-tetrate-v0","type":"application","urls":["istio/1.17.1/gateway-1.17.1.tgz"],"created":"2023-02-27T03:57:23Z","digest":"24d6494bf1c7f1ecc942b8a15c3d373e9954ea44fdb56df1e2288625f1374026"},{"name":"gateway","sources":["http://github.com/istio/istio"],"version":"1.17.3","description":"Helm chart for deploying Istio gateways","keywords":["istio","gateways"],"icon":"https://istio.io/latest/favicons/android-192x192.png","apiVersion":"v2","appVersion":"1.17.3-tetrate-v0","type":"application","urls":["istio/1.17.3/gateway-1.17.3.tgz"],"created":"2023-06-09T14:50:25Z","digest":"22f668cb6ea6836738991eedaeac3f5e6c3055330db4f1433760843eb6c849bb"},{"name":"gateway","sources":["http://github.com/istio/istio"],"version":"1.17.5","description":"Helm chart for deploying Istio gateways","keywords":["istio","gateways"],"icon":"https://istio.io/latest/favicons/android-192x192.png","apiVersion":"v2","appVersion":"1.17.5-tetrate-v0","type":"application","urls":["istio/1.17.5/gateway-1.17.5.tgz"],"created":"2023-07-28T15:12:44Z","digest":"2b99589e73fb1a1d49516778c787fb79ecaee6f543e6baccb4966df71150f02b"},{"name":"gateway","sources":["https://github.com/istio/istio"],"version":"1.18.0","description":"Helm chart for deploying Istio gateways","keywords":["istio","gateways"],"icon":"https://istio.io/latest/favicons/android-192x192.png","apiVersion":"v2","appVersion":"1.18.0-tetrate-v0","type":"application","urls":["istio/1.18.0/gateway-1.18.0.tgz"],"created":"2023-06-09T16:41:21Z","digest":"6b133dbfcc21b19914fb3e122c78d6d6713f20a6195396f862b0c94294c27440"},{"name":"gateway","sources":["https://github.com/istio/istio"],"version":"1.18.2","description":"Helm chart for deploying Istio gateways","keywords":["istio","gateways"],"icon":"https://istio.io/latest/favicons/android-192x192.png","apiVersion":"v2","appVersion":"1.18.2-tetrate-v0","type":"application","urls":["istio/1.18.2/gateway-1.18.2.tgz"],"created":"2023-07-28T15:46:16Z","digest":"90a3b2f1f29a272372911f3b25e458b2e70db2658525225eaf853c98ab65ee0f"}],"istio-default":[{"name":"istio-default","sources":["http://github.com/istio/istio"],"version":"1.13.3","description":"Helm chart for istio default revision components.","keywords":["istio"],"icon":"https://istio.io/latest/favicons/android-192x192.png","apiVersion":"v1","appVersion":"1.0.0","urls":["istio/1.13.3/istio-default-1.13.3.tgz"],"created":"2022-05-04T21:03:38Z","digest":"18c398d73f38c3809e925cfb089977d9981919d098268a6d2112a9b5bbaf09a2"},{"name":"istio-default","sources":["http://github.com/istio/istio"],"version":"1.13.5","description":"Helm chart for istio default revision components.","keywords":["istio"],"icon":"https://istio.io/latest/favicons/android-192x192.png","apiVersion":"v1","appVersion":"1.0.0","urls":["istio/1.13.5/istio-default-1.13.5.tgz"],"created":"2022-06-13T16:19:44Z","digest":"d6aa78310ba0b5c4e6bbdfa01caaa61895f90500152219dadc8cdcdb04aa83f2"},{"name":"istio-default","sources":["http://github.com/istio/istio"],"version":"1.14.1","description":"Helm chart for istio default revision components.","keywords":["istio"],"icon":"https://istio.io/latest/favicons/android-192x192.png","apiVersion":"v1","appVersion":"1.0.0","urls":["istio/1.14.1/istio-default-1.14.1.tgz"],"created":"2022-07-07T15:27:26Z","digest":"102e262e413e8d85efe4df596694e236e7550eaa3467d60b7a3ee7ca970b5dd5"},{"name":"istio-default","sources":["http://github.com/istio/istio"],"version":"1.14.3","description":"Helm chart for istio default revision components.","keywords":["istio"],"icon":"https://istio.io/latest/favicons/android-192x192.png","apiVersion":"v1","appVersion":"1.0.0","urls":["istio/1.14.3/istio-default-1.14.3.tgz"],"created":"2022-08-05T15:02:57Z","digest":"d4c26f492291ae94717ea52e395de7e945fd7dccb71897ec9fbf1ed81790c20a"},{"name":"istio-default","sources":["http://github.com/istio/istio"],"version":"1.14.5","description":"Helm chart for istio default revision components.","keywords":["istio"],"icon":"https://istio.io/latest/favicons/android-192x192.png","apiVersion":"v1","appVersion":"1.0.0","urls":["istio/1.14.5/istio-default-1.14.5.tgz"],"created":"2022-10-27T21:03:09Z","digest":"212105c9cb854a7cf5820846dee62f367d735fa281289280bd656c1fa62448de"},{"name":"istio-default","sources":["http://github.com/istio/istio"],"version":"1.14.6","description":"Helm chart for istio default revision components.","keywords":["istio"],"icon":"https://istio.io/latest/favicons/android-192x192.png","apiVersion":"v1","appVersion":"1.0.0","urls":["istio/1.14.6/istio-default-1.14.6.tgz"],"created":"2022-12-14T19:21:21Z","digest":"837019c9bfb70c09a5bca9202234e968ae65b753306620db2e750ee351aa67b1"},{"name":"istio-default","sources":["http://github.com/istio/istio"],"version":"1.15.4","description":"Helm chart for istio default revision components.","keywords":["istio"],"icon":"https://istio.io/latest/favicons/android-192x192.png","apiVersion":"v1","appVersion":"1.0.0","urls":["istio/1.15.4/istio-default-1.15.4.tgz"],"created":"2023-01-24T00:42:53Z","digest":"da7c3c19b4716856c7823e51750335504633220085b514010ba991ae931087f7"},{"name":"istio-default","sources":["http://github.com/istio/istio"],"version":"1.16.2","description":"Helm chart for istio default revision components.","keywords":["istio"],"icon":"https://istio.io/latest/favicons/android-192x192.png","apiVersion":"v1","appVersion":"1.0.0","urls":["istio/1.16.2/istio-default-1.16.2.tgz"],"created":"2023-02-05T16:43:09Z","digest":"add1f91bffe529bb7da5bc07cf166ac7b1ffb97cceba09af4f2df08143c29ee9"},{"name":"istio-default","sources":["http://github.com/istio/istio"],"version":"1.16.4","description":"Helm chart for istio default revision components.","keywords":["istio"],"icon":"https://istio.io/latest/favicons/android-192x192.png","apiVersion":"v1","appVersion":"1.0.0","urls":["istio/1.16.4/istio-default-1.16.4.tgz"],"created":"2023-07-19T06:52:29Z","digest":"a417cca735e43ab4c8ff9543df3f9af6917f677c903755568b35f7c7741b35af"},{"name":"istio-default","sources":["http://github.com/istio/istio"],"version":"1.16.5","description":"Helm chart for istio default revision components.","keywords":["istio"],"icon":"https://istio.io/latest/favicons/android-192x192.png","apiVersion":"v1","appVersion":"1.0.0","urls":["istio/1.16.5/istio-default-1.16.5.tgz"],"created":"2023-05-26T03:29:11Z","digest":"00cc2379b33567ab7f048fa80dfa0e6b86ceee0cc2b8d70686f4bb3efc4a9cd2"},{"name":"istio-default","sources":["http://github.com/istio/istio"],"version":"1.16.7","description":"Helm chart for istio default revision components.","keywords":["istio"],"icon":"https://istio.io/latest/favicons/android-192x192.png","apiVersion":"v1","appVersion":"1.0.0","urls":["istio/1.16.7/istio-default-1.16.7.tgz"],"created":"2023-07-28T16:04:01Z","digest":"ad0969f9512c44ec7075ab91799d5dc579d2ef35ce63f22ef4d6f8fb388090b6"},{"name":"istio-default","sources":["http://github.com/istio/istio"],"version":"1.17.1","description":"Helm chart for istio default revision components.","keywords":["istio"],"icon":"https://istio.io/latest/favicons/android-192x192.png","apiVersion":"v1","appVersion":"1.0.0","urls":["istio/1.17.1/istio-default-1.17.1.tgz"],"created":"2023-02-27T03:57:23Z","digest":"8f83bed35e8e372abba14f87ab55ff5fe8de876cf7329b40821432e60781d9c8"},{"name":"istio-default","sources":["http://github.com/istio/istio"],"version":"1.17.3","description":"Helm chart for istio default revision components.","keywords":["istio"],"icon":"https://istio.io/latest/favicons/android-192x192.png","apiVersion":"v1","appVersion":"1.0.0","urls":["istio/1.17.3/istio-default-1.17.3.tgz"],"created":"2023-06-09T14:50:25Z","digest":"9b02df3cf71bfb184a9376a8eb5233328dd217dffc70b22733c522e24be134e6"},{"name":"istio-default","sources":["http://github.com/istio/istio"],"version":"1.17.5","description":"Helm chart for istio default revision components.","keywords":["istio"],"icon":"https://istio.io/latest/favicons/android-192x192.png","apiVersion":"v1","appVersion":"1.0.0","urls":["istio/1.17.5/istio-default-1.17.5.tgz"],"created":"2023-07-28T15:12:44Z","digest":"88c459f71f2de29382c8401aa491cbe579e1a13c066a41d7504f8c2907c6d558"},{"name":"istio-default","sources":["https://github.com/istio/istio"],"version":"1.18.0","description":"Helm chart for istio default revision components.","keywords":["istio"],"icon":"https://istio.io/latest/favicons/android-192x192.png","apiVersion":"v1","appVersion":"1.0.0","urls":["istio/1.18.0/istio-default-1.18.0.tgz"],"created":"2023-06-09T16:41:21Z","digest":"6050ae19e7c66faaa43bbdb0f1831a55c1f7f8818d85a6272e9053594e4d89d4"},{"name":"istio-default","sources":["https://github.com/istio/istio"],"version":"1.18.2","description":"Helm chart for istio default revision components.","keywords":["istio"],"icon":"https://istio.io/latest/favicons/android-192x192.png","apiVersion":"v1","appVersion":"1.0.0","urls":["istio/1.18.2/istio-default-1.18.2.tgz"],"created":"2023-07-28T15:46:16Z","digest":"c463c780fd4aea14b284d59859666177babb4650dbef57be00e50b6f13ac9f80"}],"istio-egress":[{"name":"istio-egress","sources":["http://github.com/istio/istio"],"version":"1.13.3","description":"Helm chart for deploying Istio gateways","keywords":["istio","egressgateway","gateways"],"icon":"https://istio.io/latest/favicons/android-192x192.png","apiVersion":"v1","appVersion":"1.13.3-tetrate-v0","urls":["istio/1.13.3/istio-egress-1.13.3.tgz"],"created":"2022-05-04T21:03:38Z","digest":"8751c9d993836e67d0c846587a1b32b88baca1752248083ac62664bb2af334de"},{"name":"istio-egress","sources":["http://github.com/istio/istio"],"version":"1.13.5","description":"Helm chart for deploying Istio gateways","keywords":["istio","egressgateway","gateways"],"icon":"https://istio.io/latest/favicons/android-192x192.png","apiVersion":"v1","appVersion":"1.13.5-tetrate-v0","urls":["istio/1.13.5/istio-egress-1.13.5.tgz"],"created":"2022-06-13T16:19:44Z","digest":"66bf5cbb9701e490de89a6ce267ee7160f44c851dcc801468c2b7c0b6fe75b54"},{"name":"istio-egress","sources":["http://github.com/istio/istio"],"version":"1.14.1","description":"Helm chart for deploying Istio gateways","keywords":["istio","egressgateway","gateways"],"icon":"https://istio.io/latest/favicons/android-192x192.png","apiVersion":"v1","appVersion":"1.14.1-tetrate-v0","urls":["istio/1.14.1/istio-egress-1.14.1.tgz"],"created":"2022-07-07T15:27:26Z","digest":"be4aa3cf97dc7eff120f6f4e1b5d5c465aca90ddb6507df05a1a4fe09cb525de"},{"name":"istio-egress","sources":["http://github.com/istio/istio"],"version":"1.14.3","description":"Helm chart for deploying Istio gateways","keywords":["istio","egressgateway","gateways"],"icon":"https://istio.io/latest/favicons/android-192x192.png","apiVersion":"v1","appVersion":"1.14.3-tetrate-v0","urls":["istio/1.14.3/istio-egress-1.14.3.tgz"],"created":"2022-08-05T15:02:57Z","digest":"057ab172dfce02d70a3c1a0cd4be969c4be4fc98f7f48796e26e73883261f456"},{"name":"istio-egress","sources":["http://github.com/istio/istio"],"version":"1.14.5","description":"Helm chart for deploying Istio gateways","keywords":["istio","egressgateway","gateways"],"icon":"https://istio.io/latest/favicons/android-192x192.png","apiVersion":"v1","appVersion":"1.14.5-tetrate-v0","urls":["istio/1.14.5/istio-egress-1.14.5.tgz"],"created":"2022-10-27T21:03:09Z","digest":"c151dcda80a1007810b6f2c6c465feb6b678f051c439885f883deff693a71562"},{"name":"istio-egress","sources":["http://github.com/istio/istio"],"version":"1.14.6","description":"Helm chart for deploying Istio gateways","keywords":["istio","egressgateway","gateways"],"icon":"https://istio.io/latest/favicons/android-192x192.png","apiVersion":"v1","appVersion":"1.14.6-tetrate-v0","urls":["istio/1.14.6/istio-egress-1.14.6.tgz"],"created":"2022-12-14T19:21:21Z","digest":"c48c93f1325f74bbc93e1122de5395bb9060a04f8659eff8efb36b1496620ef3"},{"name":"istio-egress","sources":["http://github.com/istio/istio"],"version":"1.15.4","description":"Helm chart for deploying Istio gateways","keywords":["istio","egressgateway","gateways"],"icon":"https://istio.io/latest/favicons/android-192x192.png","apiVersion":"v1","appVersion":"1.15.4-tetrate-v0","urls":["istio/1.15.4/istio-egress-1.15.4.tgz"],"created":"2023-01-24T00:42:53Z","digest":"83dd3a62c223e0dd61c7a0ed5549d102b89a589a3d8832ed61b3af25ece609e3"},{"name":"istio-egress","sources":["http://github.com/istio/istio"],"version":"1.16.2","description":"Helm chart for deploying Istio gateways","keywords":["istio","egressgateway","gateways"],"icon":"https://istio.io/latest/favicons/android-192x192.png","apiVersion":"v1","appVersion":"1.16.2-tetrate-v0","urls":["istio/1.16.2/istio-egress-1.16.2.tgz"],"created":"2023-02-05T16:43:09Z","digest":"e436e3968a2a97d19b30c2fcc442fe6f8005cff101ee4131d1f6756731028522"},{"name":"istio-egress","sources":["http://github.com/istio/istio"],"version":"1.16.4","description":"Helm chart for deploying Istio gateways","keywords":["istio","egressgateway","gateways"],"icon":"https://istio.io/latest/favicons/android-192x192.png","apiVersion":"v1","appVersion":"1.16.4-tetrate-v4","urls":["istio/1.16.4/istio-egress-1.16.4.tgz"],"created":"2023-07-19T06:52:29Z","digest":"491d297deeb2c69984a2f77be6699fe1008f91edb39ec28e8a540f303e3ceeda"},{"name":"istio-egress","sources":["http://github.com/istio/istio"],"version":"1.16.5","description":"Helm chart for deploying Istio gateways","keywords":["istio","egressgateway","gateways"],"icon":"https://istio.io/latest/favicons/android-192x192.png","apiVersion":"v1","appVersion":"1.16.5-tetrate-v0","urls":["istio/1.16.5/istio-egress-1.16.5.tgz"],"created":"2023-05-26T03:29:11Z","digest":"4abe723a5fed7e856c5706932daaac3326011b264e618849b0469ea2bd34ef85"},{"name":"istio-egress","sources":["http://github.com/istio/istio"],"version":"1.16.7","description":"Helm chart for deploying Istio gateways","keywords":["istio","egressgateway","gateways"],"icon":"https://istio.io/latest/favicons/android-192x192.png","apiVersion":"v1","appVersion":"1.16.7-tetrate-v0","urls":["istio/1.16.7/istio-egress-1.16.7.tgz"],"created":"2023-07-28T16:04:01Z","digest":"f7acdfdfa1a64dbf6a7a748719ed3b79251b376991d99da088f30500096862cf"},{"name":"istio-egress","sources":["http://github.com/istio/istio"],"version":"1.17.1","description":"Helm chart for deploying Istio gateways","keywords":["istio","egressgateway","gateways"],"icon":"https://istio.io/latest/favicons/android-192x192.png","apiVersion":"v1","appVersion":"1.17.1-tetrate-v0","urls":["istio/1.17.1/istio-egress-1.17.1.tgz"],"created":"2023-02-27T03:57:23Z","digest":"e4fcfff8f5d46429f18243dfa248ec2da5d97a7a313ea44054d77e88aeee93d0"},{"name":"istio-egress","sources":["http://github.com/istio/istio"],"version":"1.17.3","description":"Helm chart for deploying Istio gateways","keywords":["istio","egressgateway","gateways"],"icon":"https://istio.io/latest/favicons/android-192x192.png","apiVersion":"v1","appVersion":"1.17.3-tetrate-v0","urls":["istio/1.17.3/istio-egress-1.17.3.tgz"],"created":"2023-06-09T14:50:25Z","digest":"690085c2f0033ecf7108a40721386bedca0fe3f565f1a1c36684bb1d66be2560"},{"name":"istio-egress","sources":["http://github.com/istio/istio"],"version":"1.17.5","description":"Helm chart for deploying Istio gateways","keywords":["istio","egressgateway","gateways"],"icon":"https://istio.io/latest/favicons/android-192x192.png","apiVersion":"v1","appVersion":"1.17.5-tetrate-v0","urls":["istio/1.17.5/istio-egress-1.17.5.tgz"],"created":"2023-07-28T15:12:44Z","digest":"d34c9722311b8e30cd22f22a5b280ddc7b2498b504439f1d07300e2823c23e7a"},{"name":"istio-egress","sources":["https://github.com/istio/istio"],"version":"1.18.0","description":"Helm chart for deploying Istio gateways","keywords":["istio","egressgateway","gateways"],"icon":"https://istio.io/latest/favicons/android-192x192.png","apiVersion":"v1","appVersion":"1.18.0-tetrate-v0","urls":["istio/1.18.0/istio-egress-1.18.0.tgz"],"created":"2023-06-09T16:41:21Z","digest":"08fca2839a05b366788981076b34f929fe5c079440da05c0822ebf80daa49159"},{"name":"istio-egress","sources":["https://github.com/istio/istio"],"version":"1.18.2","description":"Helm chart for deploying Istio gateways","keywords":["istio","egressgateway","gateways"],"icon":"https://istio.io/latest/favicons/android-192x192.png","apiVersion":"v1","appVersion":"1.18.2-tetrate-v0","urls":["istio/1.18.2/istio-egress-1.18.2.tgz"],"created":"2023-07-28T15:46:16Z","digest":"f83f379f28b744a1a677d28ce0020c8016a585b17dc92655b9433a8bdf286cfa"}],"istio-ingress":[{"name":"istio-ingress","sources":["http://github.com/istio/istio"],"version":"1.13.3","description":"Helm chart for deploying Istio gateways","keywords":["istio","ingressgateway","gateways"],"icon":"https://istio.io/latest/favicons/android-192x192.png","apiVersion":"v1","appVersion":"1.13.3-tetrate-v0","urls":["istio/1.13.3/istio-ingress-1.13.3.tgz"],"created":"2022-05-04T21:03:38Z","digest":"569afb43962e40c5dc02d23c6c09c6644611b3cfd74e62152fc06f8698f44338"},{"name":"istio-ingress","sources":["http://github.com/istio/istio"],"version":"1.13.5","description":"Helm chart for deploying Istio gateways","keywords":["istio","ingressgateway","gateways"],"icon":"https://istio.io/latest/favicons/android-192x192.png","apiVersion":"v1","appVersion":"1.13.5-tetrate-v0","urls":["istio/1.13.5/istio-ingress-1.13.5.tgz"],"created":"2022-06-13T16:19:44Z","digest":"90f906fe79c098c39681c7e4bc5d1b1669d5e39729b64a8da3b729bb55ec9f16"},{"name":"istio-ingress","sources":["http://github.com/istio/istio"],"version":"1.14.1","description":"Helm chart for deploying Istio gateways","keywords":["istio","ingressgateway","gateways"],"icon":"https://istio.io/latest/favicons/android-192x192.png","apiVersion":"v1","appVersion":"1.14.1-tetrate-v0","urls":["istio/1.14.1/istio-ingress-1.14.1.tgz"],"created":"2022-07-07T15:27:26Z","digest":"cb7847487d615e9ebb062dea3e85ceb778d6d264e4520d22ae3a6b162af59122"},{"name":"istio-ingress","sources":["http://github.com/istio/istio"],"version":"1.14.3","description":"Helm chart for deploying Istio gateways","keywords":["istio","ingressgateway","gateways"],"icon":"https://istio.io/latest/favicons/android-192x192.png","apiVersion":"v1","appVersion":"1.14.3-tetrate-v0","urls":["istio/1.14.3/istio-ingress-1.14.3.tgz"],"created":"2022-08-05T15:02:57Z","digest":"265775f1008ed6520a30034f3e0fe2a6fd2e7f7d006683432870d739488aa918"},{"name":"istio-ingress","sources":["http://github.com/istio/istio"],"version":"1.14.5","description":"Helm chart for deploying Istio gateways","keywords":["istio","ingressgateway","gateways"],"icon":"https://istio.io/latest/favicons/android-192x192.png","apiVersion":"v1","appVersion":"1.14.5-tetrate-v0","urls":["istio/1.14.5/istio-ingress-1.14.5.tgz"],"created":"2022-10-27T21:03:09Z","digest":"8ed9398fd2c84880a9770af0ab35a905a94ca4f75f74e7b236431e76c4a73e9d"},{"name":"istio-ingress","sources":["http://github.com/istio/istio"],"version":"1.14.6","description":"Helm chart for deploying Istio gateways","keywords":["istio","ingressgateway","gateways"],"icon":"https://istio.io/latest/favicons/android-192x192.png","apiVersion":"v1","appVersion":"1.14.6-tetrate-v0","urls":["istio/1.14.6/istio-ingress-1.14.6.tgz"],"created":"2022-12-14T19:21:21Z","digest":"9443d86895f3fef6aaeed860a297c195f7caa663eba9f7fc6d9cc6f762d2a433"},{"name":"istio-ingress","sources":["http://github.com/istio/istio"],"version":"1.15.4","description":"Helm chart for deploying Istio gateways","keywords":["istio","ingressgateway","gateways"],"icon":"https://istio.io/latest/favicons/android-192x192.png","apiVersion":"v1","appVersion":"1.15.4-tetrate-v0","urls":["istio/1.15.4/istio-ingress-1.15.4.tgz"],"created":"2023-01-24T00:42:53Z","digest":"7b00a4885e5510b5472687815ba077fb779f7ca10f4f091b0ad882337b7e0c75"},{"name":"istio-ingress","sources":["http://github.com/istio/istio"],"version":"1.16.2","description":"Helm chart for deploying Istio gateways","keywords":["istio","ingressgateway","gateways"],"icon":"https://istio.io/latest/favicons/android-192x192.png","apiVersion":"v1","appVersion":"1.16.2-tetrate-v0","urls":["istio/1.16.2/istio-ingress-1.16.2.tgz"],"created":"2023-02-05T16:43:09Z","digest":"adae34494c5f8c3459756913f723a33b47f27878642959dbff8ce903d10b3372"},{"name":"istio-ingress","sources":["http://github.com/istio/istio"],"version":"1.16.4","description":"Helm chart for deploying Istio gateways","keywords":["istio","ingressgateway","gateways"],"icon":"https://istio.io/latest/favicons/android-192x192.png","apiVersion":"v1","appVersion":"1.16.4-tetrate-v4","urls":["istio/1.16.4/istio-ingress-1.16.4.tgz"],"created":"2023-07-19T06:52:29Z","digest":"b4e03c217bda6a6d64add4af1d94010e344fbdc632065cc7466de351130231aa"},{"name":"istio-ingress","sources":["http://github.com/istio/istio"],"version":"1.16.5","description":"Helm chart for deploying Istio gateways","keywords":["istio","ingressgateway","gateways"],"icon":"https://istio.io/latest/favicons/android-192x192.png","apiVersion":"v1","appVersion":"1.16.5-tetrate-v0","urls":["istio/1.16.5/istio-ingress-1.16.5.tgz"],"created":"2023-05-26T03:29:11Z","digest":"68e444d806aab27938adfc85c242513ad27a1939c6e259826efccdcf622d5d08"},{"name":"istio-ingress","sources":["http://github.com/istio/istio"],"version":"1.16.7","description":"Helm chart for deploying Istio gateways","keywords":["istio","ingressgateway","gateways"],"icon":"https://istio.io/latest/favicons/android-192x192.png","apiVersion":"v1","appVersion":"1.16.7-tetrate-v0","urls":["istio/1.16.7/istio-ingress-1.16.7.tgz"],"created":"2023-07-28T16:04:01Z","digest":"8ecc94025f120ce575e75a9f51abe45bf7a969a932042be0181df2aca34913c1"},{"name":"istio-ingress","sources":["http://github.com/istio/istio"],"version":"1.17.1","description":"Helm chart for deploying Istio gateways","keywords":["istio","ingressgateway","gateways"],"icon":"https://istio.io/latest/favicons/android-192x192.png","apiVersion":"v1","appVersion":"1.17.1-tetrate-v0","urls":["istio/1.17.1/istio-ingress-1.17.1.tgz"],"created":"2023-02-27T03:57:23Z","digest":"9cb470022e1a2108a082adcd03dcf6777adb6362a8245639ccd381a5e93e4434"},{"name":"istio-ingress","sources":["http://github.com/istio/istio"],"version":"1.17.3","description":"Helm chart for deploying Istio gateways","keywords":["istio","ingressgateway","gateways"],"icon":"https://istio.io/latest/favicons/android-192x192.png","apiVersion":"v1","appVersion":"1.17.3-tetrate-v0","urls":["istio/1.17.3/istio-ingress-1.17.3.tgz"],"created":"2023-06-09T14:50:25Z","digest":"442a97ccbef20e83916750191bb9c3743ac33e22cc06523a75456fffbebfb1c0"},{"name":"istio-ingress","sources":["http://github.com/istio/istio"],"version":"1.17.5","description":"Helm chart for deploying Istio gateways","keywords":["istio","ingressgateway","gateways"],"icon":"https://istio.io/latest/favicons/android-192x192.png","apiVersion":"v1","appVersion":"1.17.5-tetrate-v0","urls":["istio/1.17.5/istio-ingress-1.17.5.tgz"],"created":"2023-07-28T15:12:44Z","digest":"daedfde5bb5612250d14b9c136c2f262c1707447d1815a6bab360ebe2cdf90fc"},{"name":"istio-ingress","sources":["http://github.com/istio/istio"],"version":"1.18.0","description":"Helm chart for deploying Istio gateways","keywords":["istio","ingressgateway","gateways"],"icon":"https://istio.io/latest/favicons/android-192x192.png","apiVersion":"v1","appVersion":"1.18.0-tetrate-v0","urls":["istio/1.18.0/istio-ingress-1.18.0.tgz"],"created":"2023-06-09T16:41:21Z","digest":"4352d31c4e099873756f7b1b5dee574a06ddf0cbc93d6973de5ce3df211ebe03"},{"name":"istio-ingress","sources":["http://github.com/istio/istio"],"version":"1.18.2","description":"Helm chart for deploying Istio gateways","keywords":["istio","ingressgateway","gateways"],"icon":"https://istio.io/latest/favicons/android-192x192.png","apiVersion":"v1","appVersion":"1.18.2-tetrate-v0","urls":["istio/1.18.2/istio-ingress-1.18.2.tgz"],"created":"2023-07-28T15:46:16Z","digest":"e72773a9273b45a26aec4f100d4aace0f362aed5f362208e2545d6e0ee0c248c"}],"istio-monitoring":[{"name":"istio-monitoring","version":"0.1.1","description":"A Helm chart for Kubernetes","apiVersion":"v2","appVersion":"v0.1.1","annotations":{"tetrate.io/addon":"true"},"dependencies":[{"name":"grafana","version":"6.58.4","repository":"https://grafana.github.io/helm-charts","condition":"grafana.enabled"},{"name":"prometheus","version":"19.6.1","repository":"https://prometheus-community.github.io/helm-charts","condition":"prometheus.enabled"}],"type":"application","urls":["addons/istio-monitoring-0.1.1.tgz"],"created":"2023-09-13T13:59:06.131926174Z","digest":"691fdfb46ea674d93d3116f3496b7bb2dc8e332889e06f74971f2288cde1fcc6"},{"name":"istio-monitoring","version":"0.1.2","description":"A Helm chart for deploying Istio Monitoring","apiVersion":"v2","appVersion":"v0.1.1","annotations":{"tetrate.io/addon":"true"},"dependencies":[{"name":"grafana","version":"6.58.4","repository":"https://grafana.github.io/helm-charts","condition":"grafana.enabled"},{"name":"prometheus","version":"19.6.1","repository":"https://prometheus-community.github.io/helm-charts","condition":"prometheus.enabled"}],"type":"application","urls":["addons/istio-monitoring-0.1.2.tgz"],"created":"2023-09-13T13:59:38.571754732Z","digest":"aaf981545df5aad9f2ba120166783159a5b9dba6176d363fbd551094af956d78"}],"istio-operator":[{"name":"istio-operator","sources":["https://github.com/istio/istio/tree/master/operator"],"version":"1.13.3","description":"Helm chart for deploying Istio operator","keywords":["istio","operator"],"icon":"https://istio.io/latest/favicons/android-192x192.png","apiVersion":"v1","appVersion":"1.13.3-tetrate-v0","urls":["istio/1.13.3/istio-operator-1.13.3.tgz"],"created":"2022-05-04T21:03:38Z","digest":"90acefa3f232b5bf691d62b612b6f6051073ca13a84d78ceb9845d083e8bee22"},{"name":"istio-operator","sources":["https://github.com/istio/istio/tree/master/operator"],"version":"1.13.5","description":"Helm chart for deploying Istio operator","keywords":["istio","operator"],"icon":"https://istio.io/latest/favicons/android-192x192.png","apiVersion":"v1","appVersion":"1.13.5-tetrate-v0","urls":["istio/1.13.5/istio-operator-1.13.5.tgz"],"created":"2022-06-13T16:19:44Z","digest":"1dce7990c2135d3d9fcf9d33411403fa47e24bc88765020f79522ebb9e6691ac"},{"name":"istio-operator","sources":["https://github.com/istio/istio/tree/master/operator"],"version":"1.14.1","description":"Helm chart for deploying Istio operator","keywords":["istio","operator"],"icon":"https://istio.io/latest/favicons/android-192x192.png","apiVersion":"v1","appVersion":"1.14.1-tetrate-v0","urls":["istio/1.14.1/istio-operator-1.14.1.tgz"],"created":"2022-07-07T15:27:26Z","digest":"d75a04b7677533f875fb101f9b04a86541b7a8e7ec3422357604d42caeaa3199"},{"name":"istio-operator","sources":["https://github.com/istio/istio/tree/master/operator"],"version":"1.14.3","description":"Helm chart for deploying Istio operator","keywords":["istio","operator"],"icon":"https://istio.io/latest/favicons/android-192x192.png","apiVersion":"v1","appVersion":"1.14.3-tetrate-v0","urls":["istio/1.14.3/istio-operator-1.14.3.tgz"],"created":"2022-08-05T15:02:57Z","digest":"aa8780fecd36807b3e5d19061565920d00f5902d813484cdfffb37dd2876f96a"},{"name":"istio-operator","sources":["https://github.com/istio/istio/tree/master/operator"],"version":"1.14.5","description":"Helm chart for deploying Istio operator","keywords":["istio","operator"],"icon":"https://istio.io/latest/favicons/android-192x192.png","apiVersion":"v1","appVersion":"1.14.5-tetrate-v0","urls":["istio/1.14.5/istio-operator-1.14.5.tgz"],"created":"2022-10-27T21:03:09Z","digest":"499ec71bff9c49a762cb65e7e2f7904988097e6c38e501deee62bd4017e57a52"},{"name":"istio-operator","sources":["https://github.com/istio/istio/tree/master/operator"],"version":"1.14.6","description":"Helm chart for deploying Istio operator","keywords":["istio","operator"],"icon":"https://istio.io/latest/favicons/android-192x192.png","apiVersion":"v1","appVersion":"1.14.6-tetrate-v0","urls":["istio/1.14.6/istio-operator-1.14.6.tgz"],"created":"2022-12-14T19:21:21Z","digest":"b9734f4eb6c614451a7a9b9caaafd8f719a5121e68698011df0df3c24f6faa5e"},{"name":"istio-operator","sources":["https://github.com/istio/istio/tree/master/operator"],"version":"1.15.4","description":"Helm chart for deploying Istio operator","keywords":["istio","operator"],"icon":"https://istio.io/latest/favicons/android-192x192.png","apiVersion":"v1","appVersion":"1.15.4-tetrate-v0","urls":["istio/1.15.4/istio-operator-1.15.4.tgz"],"created":"2023-01-24T00:42:53Z","digest":"04341712349a5a73ad7bf06e2fe3f1d05b0e723844edcf763e6c9fb2adbc35b6"},{"name":"istio-operator","sources":["https://github.com/istio/istio/tree/master/operator"],"version":"1.16.2","description":"Helm chart for deploying Istio operator","keywords":["istio","operator"],"icon":"https://istio.io/latest/favicons/android-192x192.png","apiVersion":"v1","appVersion":"1.16.2-tetrate-v0","urls":["istio/1.16.2/istio-operator-1.16.2.tgz"],"created":"2023-02-05T16:43:09Z","digest":"2b73f4fc9560d067bf30c13ef66b18cc9790f3c6abde941cbf451ee49a704d7a"},{"name":"istio-operator","sources":["https://github.com/istio/istio/tree/master/operator"],"version":"1.16.4","description":"Helm chart for deploying Istio operator","keywords":["istio","operator"],"icon":"https://istio.io/latest/favicons/android-192x192.png","apiVersion":"v1","appVersion":"1.16.4-tetrate-v4","urls":["istio/1.16.4/istio-operator-1.16.4.tgz"],"created":"2023-07-19T06:52:29Z","digest":"bc09a53abf785758aee361c0f839c83a673692bb480afb04b282e65a2001696c"},{"name":"istio-operator","sources":["https://github.com/istio/istio/tree/master/operator"],"version":"1.16.5","description":"Helm chart for deploying Istio operator","keywords":["istio","operator"],"icon":"https://istio.io/latest/favicons/android-192x192.png","apiVersion":"v1","appVersion":"1.16.5-tetrate-v0","urls":["istio/1.16.5/istio-operator-1.16.5.tgz"],"created":"2023-05-26T03:29:11Z","digest":"d11036c157a41ed5afa5776103f688b928bc0d5ddbc57a3326959b1e081e82a8"},{"name":"istio-operator","sources":["https://github.com/istio/istio/tree/master/operator"],"version":"1.16.7","description":"Helm chart for deploying Istio operator","keywords":["istio","operator"],"icon":"https://istio.io/latest/favicons/android-192x192.png","apiVersion":"v1","appVersion":"1.16.7-tetrate-v0","urls":["istio/1.16.7/istio-operator-1.16.7.tgz"],"created":"2023-07-28T16:04:01Z","digest":"4eb8a243504f1cc1bece214244de9c604e221311f53b096fa4a119fbb13aec7d"},{"name":"istio-operator","sources":["https://github.com/istio/istio/tree/master/operator"],"version":"1.17.1","description":"Helm chart for deploying Istio operator","keywords":["istio","operator"],"icon":"https://istio.io/latest/favicons/android-192x192.png","apiVersion":"v1","appVersion":"1.17.1-tetrate-v0","urls":["istio/1.17.1/istio-operator-1.17.1.tgz"],"created":"2023-02-27T03:57:23Z","digest":"103cd35ff1ae1a57245979686922364ff492e882663be555619871561931616c"},{"name":"istio-operator","sources":["https://github.com/istio/istio/tree/master/operator"],"version":"1.17.3","description":"Helm chart for deploying Istio operator","keywords":["istio","operator"],"icon":"https://istio.io/latest/favicons/android-192x192.png","apiVersion":"v1","appVersion":"1.17.3-tetrate-v0","urls":["istio/1.17.3/istio-operator-1.17.3.tgz"],"created":"2023-06-09T14:50:25Z","digest":"6e81f5391fef95f76d48a976633ce6dfe0b8b636c458b96d13e4b3ab08e5932c"},{"name":"istio-operator","sources":["https://github.com/istio/istio/tree/master/operator"],"version":"1.17.5","description":"Helm chart for deploying Istio operator","keywords":["istio","operator"],"icon":"https://istio.io/latest/favicons/android-192x192.png","apiVersion":"v1","appVersion":"1.17.5-tetrate-v0","urls":["istio/1.17.5/istio-operator-1.17.5.tgz"],"created":"2023-07-28T15:12:44Z","digest":"166b5e18d7ef3f3d5d3b1382e617425155ce5cc458bc788063a82b553ce13d46"},{"name":"istio-operator","sources":["https://github.com/istio/istio/tree/master/operator"],"version":"1.18.0","description":"Helm chart for deploying Istio operator","keywords":["istio","operator"],"icon":"https://istio.io/latest/favicons/android-192x192.png","apiVersion":"v1","appVersion":"1.18.0-tetrate-v0","urls":["istio/1.18.0/istio-operator-1.18.0.tgz"],"created":"2023-06-09T16:41:21Z","digest":"d107c068dda0dfc5c9ed9a04e4cd4ba8d02f2b6e15c9ba7be98a6df03bc2b444"},{"name":"istio-operator","sources":["https://github.com/istio/istio/tree/master/operator"],"version":"1.18.2","description":"Helm chart for deploying Istio operator","keywords":["istio","operator"],"icon":"https://istio.io/latest/favicons/android-192x192.png","apiVersion":"v1","appVersion":"1.18.2-tetrate-v0","urls":["istio/1.18.2/istio-operator-1.18.2.tgz"],"created":"2023-07-28T15:46:16Z","digest":"ce67635ce5c1ddb36329996286ab259ae42aa932a442276c166b1431cb7f7403"}],"istio-registry-sync":[{"name":"istio-registry-sync","version":"0.1.1","description":"A Helm chart for deploying Istio Registry Sync","apiVersion":"v2","appVersion":"v0.3.0","annotations":{"tetrate.io/addon":"true"},"type":"application","urls":["addons/istio-registry-sync-0.1.1.tgz"],"created":"2023-09-13T13:59:38.571754732Z","digest":"ecfc598a51b8128c6d13fd930efc49ff7c96a00271d5a01f0c1e13bbe1b9adfb"}],"istiod":[{"name":"istiod","sources":["http://github.com/istio/istio"],"version":"1.13.3","description":"Helm chart for istio control plane","keywords":["istio","istiod","istio-discovery"],"icon":"https://istio.io/latest/favicons/android-192x192.png","apiVersion":"v1","appVersion":"1.13.3-tetrate-v0","urls":["istio/1.13.3/istiod-1.13.3.tgz"],"created":"2022-05-04T21:03:38Z","digest":"d9ad8d75ba6995f08416a0d8b0ad22f778dfc5b55b12819e670de4447c68054a"},{"name":"istiod","sources":["http://github.com/istio/istio"],"version":"1.13.5","description":"Helm chart for istio control plane","keywords":["istio","istiod","istio-discovery"],"icon":"https://istio.io/latest/favicons/android-192x192.png","apiVersion":"v1","appVersion":"1.13.5-tetrate-v0","urls":["istio/1.13.5/istiod-1.13.5.tgz"],"created":"2022-06-13T16:19:44Z","digest":"ef6ab51bea0be4ae6b4d1b15d085bf79408b145afa76993a95cdd85663b0fe0c"},{"name":"istiod","sources":["http://github.com/istio/istio"],"version":"1.14.1","description":"Helm chart for istio control plane","keywords":["istio","istiod","istio-discovery"],"icon":"https://istio.io/latest/favicons/android-192x192.png","apiVersion":"v1","appVersion":"1.14.1-tetrate-v0","urls":["istio/1.14.1/istiod-1.14.1.tgz"],"created":"2022-07-07T15:27:26Z","digest":"8cbfb56a9ea81f0c9f8bb89d75961a2e436784fc212dd5c0f8e07a259e2090a7"},{"name":"istiod","sources":["http://github.com/istio/istio"],"version":"1.14.3","description":"Helm chart for istio control plane","keywords":["istio","istiod","istio-discovery"],"icon":"https://istio.io/latest/favicons/android-192x192.png","apiVersion":"v1","appVersion":"1.14.3-tetrate-v0","urls":["istio/1.14.3/istiod-1.14.3.tgz"],"created":"2022-08-05T15:02:57Z","digest":"bdc227834ee7cbdcfde416cdc40814ed12d953a763da848f8e64435e7bd12f49"},{"name":"istiod","sources":["http://github.com/istio/istio"],"version":"1.14.5","description":"Helm chart for istio control plane","keywords":["istio","istiod","istio-discovery"],"icon":"https://istio.io/latest/favicons/android-192x192.png","apiVersion":"v1","appVersion":"1.14.5-tetrate-v0","urls":["istio/1.14.5/istiod-1.14.5.tgz"],"created":"2022-10-27T21:03:09Z","digest":"cc6ce47f3f82b168f8e13e60f72503c3406404342e12136ff68b38c8b10a89eb"},{"name":"istiod","sources":["http://github.com/istio/istio"],"version":"1.14.6","description":"Helm chart for istio control plane","keywords":["istio","istiod","istio-discovery"],"icon":"https://istio.io/latest/favicons/android-192x192.png","apiVersion":"v1","appVersion":"1.14.6-tetrate-v0","urls":["istio/1.14.6/istiod-1.14.6.tgz"],"created":"2022-12-14T19:21:21Z","digest":"6727163720f743622449504ed89a830067ab01d548ba94da6ebcb5e1d24811cf"},{"name":"istiod","sources":["http://github.com/istio/istio"],"version":"1.15.4","description":"Helm chart for istio control plane","keywords":["istio","istiod","istio-discovery"],"icon":"https://istio.io/latest/favicons/android-192x192.png","apiVersion":"v1","appVersion":"1.15.4-tetrate-v0","urls":["istio/1.15.4/istiod-1.15.4.tgz"],"created":"2023-01-24T00:42:53Z","digest":"e407d7cb3cf3cb4347c0613b5fa54397a8a40dc5f6727e8c40c60cf13e5c63b0"},{"name":"istiod","sources":["http://github.com/istio/istio"],"version":"1.16.2","description":"Helm chart for istio control plane","keywords":["istio","istiod","istio-discovery"],"icon":"https://istio.io/latest/favicons/android-192x192.png","apiVersion":"v1","appVersion":"1.16.2-tetrate-v0","urls":["istio/1.16.2/istiod-1.16.2.tgz"],"created":"2023-02-05T16:43:09Z","digest":"512d99ececc7bccf9bc3bf5d51fe9358ffd38d71b20c45db2c317fb6098f56db"},{"name":"istiod","sources":["http://github.com/istio/istio"],"version":"1.16.4","description":"Helm chart for istio control plane","keywords":["istio","istiod","istio-discovery"],"icon":"https://istio.io/latest/favicons/android-192x192.png","apiVersion":"v1","appVersion":"1.16.4-tetrate-v4","urls":["istio/1.16.4/istiod-1.16.4.tgz"],"created":"2023-07-19T06:52:29Z","digest":"eb65f9b4c487052a51d17437cc9b1a2789eec6d983486f4200e6af78b18a76e3"},{"name":"istiod","sources":["http://github.com/istio/istio"],"version":"1.16.5","description":"Helm chart for istio control plane","keywords":["istio","istiod","istio-discovery"],"icon":"https://istio.io/latest/favicons/android-192x192.png","apiVersion":"v1","appVersion":"1.16.5-tetrate-v0","urls":["istio/1.16.5/istiod-1.16.5.tgz"],"created":"2023-05-26T03:29:11Z","digest":"1606c0154f57c15b4cd472579398fb59c84553b004e28e568248f83df308dc84"},{"name":"istiod","sources":["http://github.com/istio/istio"],"version":"1.16.7","description":"Helm chart for istio control plane","keywords":["istio","istiod","istio-discovery"],"icon":"https://istio.io/latest/favicons/android-192x192.png","apiVersion":"v1","appVersion":"1.16.7-tetrate-v0","urls":["istio/1.16.7/istiod-1.16.7.tgz"],"created":"2023-07-28T16:04:01Z","digest":"28c4a6a8c034a4b7e49bae0e7e1bdb6a96d856634f8c3b0b5aa83eb45ab5e4ca"},{"name":"istiod","sources":["http://github.com/istio/istio"],"version":"1.17.1","description":"Helm chart for istio control plane","keywords":["istio","istiod","istio-discovery"],"icon":"https://istio.io/latest/favicons/android-192x192.png","apiVersion":"v1","appVersion":"1.17.1-tetrate-v0","urls":["istio/1.17.1/istiod-1.17.1.tgz"],"created":"2023-02-27T03:57:23Z","digest":"203152883e8353177ea914ce8a47568cfe047389050e31482bdd8ee2068a8f27"},{"name":"istiod","sources":["http://github.com/istio/istio"],"version":"1.17.3","description":"Helm chart for istio control plane","keywords":["istio","istiod","istio-discovery"],"icon":"https://istio.io/latest/favicons/android-192x192.png","apiVersion":"v1","appVersion":"1.17.3-tetrate-v0","urls":["istio/1.17.3/istiod-1.17.3.tgz"],"created":"2023-06-09T14:50:25Z","digest":"78d5bc2dc47d549f7b8876bd43edd9ce6e916a267b4b2dcf515f24effbcc9207"},{"name":"istiod","sources":["http://github.com/istio/istio"],"version":"1.17.5","description":"Helm chart for istio control plane","keywords":["istio","istiod","istio-discovery"],"icon":"https://istio.io/latest/favicons/android-192x192.png","apiVersion":"v1","appVersion":"1.17.5-tetrate-v0","urls":["istio/1.17.5/istiod-1.17.5.tgz"],"created":"2023-07-28T15:12:44Z","digest":"3df51b417bebaf71711a9bfc501c098c0f0021be6f384402e4f6aae19d58bb3a"},{"name":"istiod","sources":["https://github.com/istio/istio"],"version":"1.18.0","description":"Helm chart for istio control plane","keywords":["istio","istiod","istio-discovery"],"icon":"https://istio.io/latest/favicons/android-192x192.png","apiVersion":"v1","appVersion":"1.18.0-tetrate-v0","urls":["istio/1.18.0/istiod-1.18.0.tgz"],"created":"2023-06-09T16:41:21Z","digest":"018b880d2071cce503cc8a36963e32c7485cec700a0bfc265411d56e29219816"},{"name":"istiod","sources":["https://github.com/istio/istio"],"version":"1.18.2","description":"Helm chart for istio control plane","keywords":["istio","istiod","istio-discovery"],"icon":"https://istio.io/latest/favicons/android-192x192.png","apiVersion":"v1","appVersion":"1.18.2-tetrate-v0","urls":["istio/1.18.2/istiod-1.18.2.tgz"],"created":"2023-07-28T15:46:16Z","digest":"134f26af09e81bfe309e4fefdb07679e84dad064ed7a806544d9ed7f4d34807b"}],"istiod-remote":[{"name":"istiod-remote","sources":["http://github.com/istio/istio"],"version":"1.13.3","description":"Helm chart for a remote cluster using an external istio control plane","keywords":["istio","external-istiod"],"icon":"https://istio.io/latest/favicons/android-192x192.png","apiVersion":"v1","appVersion":"1.13.3-tetrate-v0","urls":["istio/1.13.3/istiod-remote-1.13.3.tgz"],"created":"2022-05-04T21:03:38Z","digest":"eb862eaca6ed8ef0d63597029ec546cc09d3a380b7074315aa45993ebeb0ffda"},{"name":"istiod-remote","sources":["http://github.com/istio/istio"],"version":"1.13.5","description":"Helm chart for a remote cluster using an external istio control plane","keywords":["istio","external-istiod"],"icon":"https://istio.io/latest/favicons/android-192x192.png","apiVersion":"v1","appVersion":"1.13.5-tetrate-v0","urls":["istio/1.13.5/istiod-remote-1.13.5.tgz"],"created":"2022-06-13T16:19:44Z","digest":"fb8f9264a74fee4b6d9b720875f6b33c30c4a638da04020500d43a2f2536246f"},{"name":"istiod-remote","sources":["http://github.com/istio/istio"],"version":"1.14.1","description":"Helm chart for a remote cluster using an external istio control plane","keywords":["istio","external-istiod"],"icon":"https://istio.io/latest/favicons/android-192x192.png","apiVersion":"v1","appVersion":"1.14.1-tetrate-v0","urls":["istio/1.14.1/istiod-remote-1.14.1.tgz"],"created":"2022-07-07T15:27:26Z","digest":"b0cc6942890089b82ade03d0605fcd7a3611fba1cc5e06b9ec2baf89ef7c7cce"},{"name":"istiod-remote","sources":["http://github.com/istio/istio"],"version":"1.14.3","description":"Helm chart for a remote cluster using an external istio control plane","keywords":["istio","external-istiod"],"icon":"https://istio.io/latest/favicons/android-192x192.png","apiVersion":"v1","appVersion":"1.14.3-tetrate-v0","urls":["istio/1.14.3/istiod-remote-1.14.3.tgz"],"created":"2022-08-05T15:02:57Z","digest":"3d3f66f3c77ac3d8ade108fb2fdc122f1d3f3b2a3f2026b222d54f290b642004"},{"name":"istiod-remote","sources":["http://github.com/istio/istio"],"version":"1.14.5","description":"Helm chart for a remote cluster using an external istio control plane","keywords":["istio","external-istiod"],"icon":"https://istio.io/latest/favicons/android-192x192.png","apiVersion":"v1","appVersion":"1.14.5-tetrate-v0","urls":["istio/1.14.5/istiod-remote-1.14.5.tgz"],"created":"2022-10-27T21:03:09Z","digest":"dee3cb6ef4e3684b0fa2643c74be6b7845ec2b750bcfd8d54e5cd99e7d09a726"},{"name":"istiod-remote","sources":["http://github.com/istio/istio"],"version":"1.14.6","description":"Helm chart for a remote cluster using an external istio control plane","keywords":["istio","external-istiod"],"icon":"https://istio.io/latest/favicons/android-192x192.png","apiVersion":"v1","appVersion":"1.14.6-tetrate-v0","urls":["istio/1.14.6/istiod-remote-1.14.6.tgz"],"created":"2022-12-14T19:21:21Z","digest":"d9452c80b74f5a4b4153a2da1cad2f4d31b3dd35bd5cd3085d67bc356875c29b"},{"name":"istiod-remote","sources":["http://github.com/istio/istio"],"version":"1.15.4","description":"Helm chart for a remote cluster using an external istio control plane","keywords":["istio","external-istiod"],"icon":"https://istio.io/latest/favicons/android-192x192.png","apiVersion":"v1","appVersion":"1.15.4-tetrate-v0","urls":["istio/1.15.4/istiod-remote-1.15.4.tgz"],"created":"2023-01-24T00:42:53Z","digest":"cc94f3b751e17858ef4ab706b549ef23e8b8d23e607b63e192f157e54562e314"},{"name":"istiod-remote","sources":["http://github.com/istio/istio"],"version":"1.16.2","description":"Helm chart for a remote cluster using an external istio control plane","keywords":["istio","external-istiod"],"icon":"https://istio.io/latest/favicons/android-192x192.png","apiVersion":"v1","appVersion":"1.16.2-tetrate-v0","urls":["istio/1.16.2/istiod-remote-1.16.2.tgz"],"created":"2023-02-05T16:43:09Z","digest":"87b44880a78b1372ccce5c866670919bc777b3bbdb12ef9ca6efbed5aaf9763c"},{"name":"istiod-remote","sources":["http://github.com/istio/istio"],"version":"1.16.4","description":"Helm chart for a remote cluster using an external istio control plane","keywords":["istio","external-istiod"],"icon":"https://istio.io/latest/favicons/android-192x192.png","apiVersion":"v1","appVersion":"1.16.4-tetrate-v4","urls":["istio/1.16.4/istiod-remote-1.16.4.tgz"],"created":"2023-07-19T06:52:29Z","digest":"b11e8f63aa267deedfc993c935056ab8b357d27ab25cf7f0b7d8d6a7b890af22"},{"name":"istiod-remote","sources":["http://github.com/istio/istio"],"version":"1.16.5","description":"Helm chart for a remote cluster using an external istio control plane","keywords":["istio","external-istiod"],"icon":"https://istio.io/latest/favicons/android-192x192.png","apiVersion":"v1","appVersion":"1.16.5-tetrate-v0","urls":["istio/1.16.5/istiod-remote-1.16.5.tgz"],"created":"2023-05-26T03:29:11Z","digest":"4f3111cfd82c62a2523f79f6e15bc91e736442df26b7e910058c7aeb77d525ad"},{"name":"istiod-remote","sources":["http://github.com/istio/istio"],"version":"1.16.7","description":"Helm chart for a remote cluster using an external istio control plane","keywords":["istio","external-istiod"],"icon":"https://istio.io/latest/favicons/android-192x192.png","apiVersion":"v1","appVersion":"1.16.7-tetrate-v0","urls":["istio/1.16.7/istiod-remote-1.16.7.tgz"],"created":"2023-07-28T16:04:01Z","digest":"4856daabbb3a1f7999f07f8d3065648c74a55eccdf4208cfd8621ee33f875551"},{"name":"istiod-remote","sources":["http://github.com/istio/istio"],"version":"1.17.1","description":"Helm chart for a remote cluster using an external istio control plane","keywords":["istio","external-istiod"],"icon":"https://istio.io/latest/favicons/android-192x192.png","apiVersion":"v1","appVersion":"1.17.1-tetrate-v0","urls":["istio/1.17.1/istiod-remote-1.17.1.tgz"],"created":"2023-02-27T03:57:23Z","digest":"3271dedded31577f76abd0892a6a7a1892a38d3f4a9dfc5d1c60fc78159dbb55"},{"name":"istiod-remote","sources":["http://github.com/istio/istio"],"version":"1.17.3","description":"Helm chart for a remote cluster using an external istio control plane","keywords":["istio","external-istiod"],"icon":"https://istio.io/latest/favicons/android-192x192.png","apiVersion":"v1","appVersion":"1.17.3-tetrate-v0","urls":["istio/1.17.3/istiod-remote-1.17.3.tgz"],"created":"2023-06-09T14:50:25Z","digest":"0cae18da5614234224a294fd19e16fa1525e7279ae9c0f5db56f43ff7b3197cb"},{"name":"istiod-remote","sources":["http://github.com/istio/istio"],"version":"1.17.5","description":"Helm chart for a remote cluster using an external istio control plane","keywords":["istio","external-istiod"],"icon":"https://istio.io/latest/favicons/android-192x192.png","apiVersion":"v1","appVersion":"1.17.5-tetrate-v0","urls":["istio/1.17.5/istiod-remote-1.17.5.tgz"],"created":"2023-07-28T15:12:44Z","digest":"989d865ca73ab1662f232160f6543bb40e01ed53212caa00371f7791d93caf22"},{"name":"istiod-remote","sources":["https://github.com/istio/istio"],"version":"1.18.0","description":"Helm chart for a remote cluster using an external istio control plane","keywords":["istio","external-istiod"],"icon":"https://istio.io/latest/favicons/android-192x192.png","apiVersion":"v1","appVersion":"1.18.0-tetrate-v0","urls":["istio/1.18.0/istiod-remote-1.18.0.tgz"],"created":"2023-06-09T16:41:21Z","digest":"b89d78970756c9f3274782323aa16c82b94cb9e0735528ff1333ffdb5e60806f"},{"name":"istiod-remote","sources":["https://github.com/istio/istio"],"version":"1.18.2","description":"Helm chart for a remote cluster using an external istio control plane","keywords":["istio","external-istiod"],"icon":"https://istio.io/latest/favicons/android-192x192.png","apiVersion":"v1","appVersion":"1.18.2-tetrate-v0","urls":["istio/1.18.2/istiod-remote-1.18.2.tgz"],"created":"2023-07-28T15:46:16Z","digest":"6efe537c4b473b944e2fa14a17aacfc8aabae9cce0b1ca1c8b774ff9a8e92814"}],"ztunnel":[{"name":"ztunnel","sources":["https://github.com/istio/istio"],"version":"1.18.0","description":"Helm chart for istio ztunnel components","keywords":["istio-ztunnel","istio"],"icon":"https://istio.io/latest/favicons/android-192x192.png","apiVersion":"v1","appVersion":"1.18.0-tetrate-v0","urls":["istio/1.18.0/ztunnel-1.18.0.tgz"],"created":"2023-06-09T16:41:21Z","digest":"90eb28576282e57ae2be3e17690c7766fd1b089c318eb0031cae87d8713b1385"},{"name":"ztunnel","sources":["https://github.com/istio/istio"],"version":"1.18.2","description":"Helm chart for istio ztunnel components","keywords":["istio-ztunnel","istio"],"icon":"https://istio.io/latest/favicons/android-192x192.png","apiVersion":"v1","appVersion":"1.18.2-tetrate-v0","urls":["istio/1.18.2/ztunnel-1.18.2.tgz"],"created":"2023-07-28T15:46:16Z","digest":"e8f119bc4deadc4714d19cfddf64f8af30f315c75879a7b23a6bcf667c42a318"}]}},"istios":{"base":{"name":"base","sources":["https://github.com/istio/istio"],"version":"1.18.2","description":"Helm chart for deploying Istio cluster resources and CRDs","keywords":["istio"],"icon":"https://istio.io/latest/favicons/android-192x192.png","apiVersion":"v1","appVersion":"1.18.2-tetrate-v0","urls":["istio/1.18.2/base-1.18.2.tgz"],"created":"2023-07-28T15:46:16Z","digest":"c70249a967d790a78d66a3ba77ce22bc0477604e7da37d1452d7d3f7015b8c5a"},"cni":{"name":"cni","sources":["https://github.com/istio/istio/tree/master/cni"],"version":"1.18.2","description":"Helm chart for istio-cni components","keywords":["istio-cni","istio"],"icon":"https://istio.io/latest/favicons/android-192x192.png","apiVersion":"v1","appVersion":"1.18.2-tetrate-v0","urls":["istio/1.18.2/cni-1.18.2.tgz"],"created":"2023-07-28T15:46:16Z","digest":"0f3405f5edc50c81ab941fd29c4ad95f7d8a608571ba256a603e2a7e52155f59"},"gateway":{"name":"gateway","sources":["https://github.com/istio/istio"],"version":"1.18.2","description":"Helm chart for deploying Istio gateways","keywords":["istio","gateways"],"icon":"https://istio.io/latest/favicons/android-192x192.png","apiVersion":"v2","appVersion":"1.18.2-tetrate-v0","type":"application","urls":["istio/1.18.2/gateway-1.18.2.tgz"],"created":"2023-07-28T15:46:16Z","digest":"90a3b2f1f29a272372911f3b25e458b2e70db2658525225eaf853c98ab65ee0f"},"istio-default":{"name":"istio-default","sources":["https://github.com/istio/istio"],"version":"1.18.2","description":"Helm chart for istio default revision components.","keywords":["istio"],"icon":"https://istio.io/latest/favicons/android-192x192.png","apiVersion":"v1","appVersion":"1.0.0","urls":["istio/1.18.2/istio-default-1.18.2.tgz"],"created":"2023-07-28T15:46:16Z","digest":"c463c780fd4aea14b284d59859666177babb4650dbef57be00e50b6f13ac9f80"},"istio-egress":{"name":"istio-egress","sources":["https://github.com/istio/istio"],"version":"1.18.2","description":"Helm chart for deploying Istio gateways","keywords":["istio","egressgateway","gateways"],"icon":"https://istio.io/latest/favicons/android-192x192.png","apiVersion":"v1","appVersion":"1.18.2-tetrate-v0","urls":["istio/1.18.2/istio-egress-1.18.2.tgz"],"created":"2023-07-28T15:46:16Z","digest":"f83f379f28b744a1a677d28ce0020c8016a585b17dc92655b9433a8bdf286cfa"},"istio-ingress":{"name":"istio-ingress","sources":["http://github.com/istio/istio"],"version":"1.18.2","description":"Helm chart for deploying Istio gateways","keywords":["istio","ingressgateway","gateways"],"icon":"https://istio.io/latest/favicons/android-192x192.png","apiVersion":"v1","appVersion":"1.18.2-tetrate-v0","urls":["istio/1.18.2/istio-ingress-1.18.2.tgz"],"created":"2023-07-28T15:46:16Z","digest":"e72773a9273b45a26aec4f100d4aace0f362aed5f362208e2545d6e0ee0c248c"},"istio-operator":{"name":"istio-operator","sources":["https://github.com/istio/istio/tree/master/operator"],"version":"1.18.2","description":"Helm chart for deploying Istio operator","keywords":["istio","operator"],"icon":"https://istio.io/latest/favicons/android-192x192.png","apiVersion":"v1","appVersion":"1.18.2-tetrate-v0","urls":["istio/1.18.2/istio-operator-1.18.2.tgz"],"created":"2023-07-28T15:46:16Z","digest":"ce67635ce5c1ddb36329996286ab259ae42aa932a442276c166b1431cb7f7403"},"istiod":{"name":"istiod","sources":["https://github.com/istio/istio"],"version":"1.18.2","description":"Helm chart for istio control plane","keywords":["istio","istiod","istio-discovery"],"icon":"https://istio.io/latest/favicons/android-192x192.png","apiVersion":"v1","appVersion":"1.18.2-tetrate-v0","urls":["istio/1.18.2/istiod-1.18.2.tgz"],"created":"2023-07-28T15:46:16Z","digest":"134f26af09e81bfe309e4fefdb07679e84dad064ed7a806544d9ed7f4d34807b"},"istiod-remote":{"name":"istiod-remote","sources":["https://github.com/istio/istio"],"version":"1.18.2","description":"Helm chart for a remote cluster using an external istio control plane","keywords":["istio","external-istiod"],"icon":"https://istio.io/latest/favicons/android-192x192.png","apiVersion":"v1","appVersion":"1.18.2-tetrate-v0","urls":["istio/1.18.2/istiod-remote-1.18.2.tgz"],"created":"2023-07-28T15:46:16Z","digest":"6efe537c4b473b944e2fa14a17aacfc8aabae9cce0b1ca1c8b774ff9a8e92814"},"ztunnel":{"name":"ztunnel","sources":["https://github.com/istio/istio"],"version":"1.18.2","description":"Helm chart for istio ztunnel components","keywords":["istio-ztunnel","istio"],"icon":"https://istio.io/latest/favicons/android-192x192.png","apiVersion":"v1","appVersion":"1.18.2-tetrate-v0","urls":["istio/1.18.2/ztunnel-1.18.2.tgz"],"created":"2023-07-28T15:46:16Z","digest":"e8f119bc4deadc4714d19cfddf64f8af30f315c75879a7b23a6bcf667c42a318"}},"addons":{"istio-monitoring":{"name":"istio-monitoring","version":"0.1.2","description":"A Helm chart for deploying Istio Monitoring","apiVersion":"v2","appVersion":"v0.1.1","annotations":{"tetrate.io/addon":"true"},"dependencies":[{"name":"grafana","version":"6.58.4","repository":"https://grafana.github.io/helm-charts","condition":"grafana.enabled"},{"name":"prometheus","version":"19.6.1","repository":"https://prometheus-community.github.io/helm-charts","condition":"prometheus.enabled"}],"type":"application","urls":["addons/istio-monitoring-0.1.2.tgz"],"created":"2023-09-13T13:59:38.571754732Z","digest":"aaf981545df5aad9f2ba120166783159a5b9dba6176d363fbd551094af956d78"},"istio-registry-sync":{"name":"istio-registry-sync","version":"0.1.1","description":"A Helm chart for deploying Istio Registry Sync","apiVersion":"v2","appVersion":"v0.3.0","annotations":{"tetrate.io/addon":"true"},"type":"application","urls":["addons/istio-registry-sync-0.1.1.tgz"],"created":"2023-09-13T13:59:38.571754732Z","digest":"ecfc598a51b8128c6d13fd930efc49ff7c96a00271d5a01f0c1e13bbe1b9adfb"}},"systems":{"agent":{"name":"agent","version":"0.0.1","description":"Helm cart for deploying TIS agent.","apiVersion":"v2","appVersion":"0.0.1-nightly+e56ff1b","annotations":{"tetrate.io/system":"true"},"urls":["system/agent-0.0.1.tgz"],"created":"2023-09-13T13:59:06.147926088Z","digest":"74c7f7d66980acf11278a81a1c0b6a52e80308d94ac635c912e3ce838bc3dd46"}}}